render_engine_subcollections-2025.6.1.dist-info/licenses/LICENSE
subcollections/.gitignore
subcollections/__init__.py
subcollections/plugin.py
render_engine_subcollections-2025.6.1.dist-info/METADATA
render_engine_subcollections-2025.6.1.dist-info/WHEEL
render_engine_subcollections-2025.6.1.dist-info/top_level.txt
render_engine_subcollections-2025.6.1.dist-info/RECORD
