Metadata-Version: 2.4
Name: render-engine-subcollections
Version: 2025.6.1
Summary: Create subcollections based on the collection
Project-URL: homepage, https://github.com/kjaymiller/render_engine_json/
Project-URL: repository, https://github.com/kjaymiller/render_engine_json/
Requires-Python: >=3.10
License-File: LICENSE
Requires-Dist: render-engine>=2025.6.1a1
Provides-Extra: dev
Requires-Dist: pytest; extra == "dev"
Requires-Dist: ruff; extra == "dev"
Dynamic: license-file
